Metadata-Version: 1.0
Name: colorpicker-box
Version: 0.0.1
Summary: Color Picker rendered in a small boxx
Home-page: UNKNOWN
Author: Jin Cui cuijinjincui4@gmail.com
Author-email: UNKNOWN
License: MIT
Platform: UNKNOWN
